{
  "last_updated": "2026-02-20T07:30:00Z",
  "project": "project_001",
  "phase": "report_complete",
  "candidates": {
    "btc_don4h_160_25_iv": {
      "status": "validated_pass",
      "sharpe_30": 2.319,
      "sharpe_50": 2.107,
      "dsr": 0.9999,
      "max_drawdown": -0.1245,
      "n_trades": 1421,
      "notes": "Best BTC individual. 2020+ S=1.200."
    },
    "btc_don4h_60_20_iv": {
      "status": "validated_pass",
      "sharpe_30": 2.042,
      "sharpe_50": 1.808,
      "dsr": 0.9977,
      "max_drawdown": -0.1486,
      "n_trades": 941,
      "notes": "Portfolio component. Strong cost robustness."
    },
    "btc_don8h_82_20_iv": {
      "status": "validated_pass",
      "sharpe_30": 2.220,
      "sharpe_50": 2.088,
      "dsr": 0.9998,
      "max_drawdown": -0.1972,
      "n_trades": 1074,
      "notes": "Walk-forward validated: IS=2.220 -> WF=1.708 (77% retention)"
    },
    "eth_don4h_138_47_flat": {
      "status": "validated_fail",
      "sharpe_30": 2.140,
      "dsr": 0.9525,
      "max_drawdown": -0.3879,
      "notes": "FAIL: bootstrap_sharpe hard fail. MaxDD -38.8%."
    },
    "eth_don4h_164_47_flat": {
      "status": "validated_fail",
      "sharpe_30": 2.133,
      "dsr": 0.9505,
      "max_drawdown": -0.3879,
      "notes": "FAIL: bootstrap_sharpe hard fail. MaxDD -38.8%."
    },
    "eth_don8h_83_33_iv": {
      "status": "validated_conditional",
      "sharpe_30": 2.056,
      "sharpe_50": 1.971,
      "dsr": 0.9279,
      "max_drawdown": -0.0949,
      "notes": "Best ETH risk-adjusted. Primary ETH candidate for portfolio."
    },
    "eth_don4h_138_47_iv": {
      "status": "validated_conditional",
      "sharpe_30": 1.952,
      "dsr": 0.8785,
      "max_drawdown": -0.0969,
      "notes": "IV variant of eth_don4h_138_47_flat."
    },
    "eth_don4h_164_47_iv": {
      "status": "validated_conditional",
      "sharpe_30": 2.001,
      "dsr": 0.9026,
      "max_drawdown": -0.0828,
      "notes": "IV variant of eth_don4h_164_47_flat."
    }
  },
  "portfolios": {
    "btc82_30pct_eth83_70pct": {
      "status": "tier1_candidate",
      "sharpe_30bps": 2.217,
      "sharpe_50bps": 2.099,
      "dsr_30bps": 0.972,
      "max_drawdown": -0.070,
      "sharpe_2020plus": 1.943,
      "validation_verdict": "CONDITIONAL",
      "hard_fails": [],
      "soft_fails": ["walk_forward_multi", "tail_risk_analysis", "correlation_stability"],
      "strategies": [
        {"candidate": "btc_don8h_82_20_iv", "weight": 0.3},
        {"candidate": "eth_don8h_83_33_iv", "weight": 0.7}
      ],
      "btc_eth_correlation": 0.466,
      "bear_2022": {
        "btc82_sharpe": -1.688,
        "eth83_sharpe": 0.443,
        "portfolio_sharpe": -0.261,
        "portfolio_dd": -0.067
      },
      "walk_forward": {
        "wf_sharpe_30bps": 1.579,
        "wf_sharpe_50bps": 1.516,
        "retention": 0.712,
        "wf_max_drawdown": -0.059,
        "folds_positive": "4/4",
        "mean_fold_sharpe": 1.560,
        "min_fold_sharpe": 0.844,
        "verdict": "PASS"
      },
      "notes": "Champion: confirmed across 3 sessions, 55 portfolio configs. MaxDD=-7%. ETH83 saves portfolio in 2022 bear. Portfolio WF validated: 71.2% retention, all folds positive. OOS-ready pending AK approval."
    },
    "btc160_80_btc60_20_4h": {
      "status": "screened_pass",
      "sharpe_30bps": 2.334,
      "dsr_30bps": 1.000,
      "max_drawdown": -0.128,
      "sharpe_2020plus": 1.257,
      "notes": "BTC-only 4h blend. Highest raw Sharpe but S2020+=1.257 is weak. Edge concentrated in 2019."
    }
  },
  "cumulative_trials": 16269,
  "baseline_sharpe": 1.580,
  "total_portfolios_tested": 55,
  "recommendation": "btc82_30_eth83_70 ready for single-shot OOS evaluation pending AK approval"
}
